setup.py
clt_requirements/__init__.py
clt_requirements.egg-info/PKG-INFO
clt_requirements.egg-info/SOURCES.txt
clt_requirements.egg-info/dependency_links.txt
clt_requirements.egg-info/requires.txt
clt_requirements.egg-info/top_level.txt